imaging_server_kit/__init__.py
imaging_server_kit/_version.py
imaging_server_kit/cli.py
imaging_server_kit/core/__init__.py
imaging_server_kit/core/_etc.py
imaging_server_kit/core/algorithm.py
imaging_server_kit/core/app.py
imaging_server_kit/core/client.py
imaging_server_kit/core/encoding.py
imaging_server_kit/core/errors.py
imaging_server_kit/core/multialgo.py
imaging_server_kit/core/results.py
imaging_server_kit/core/runner.py
imaging_server_kit/core/serialization.py
imaging_server_kit/core/tiling.py
imaging_server_kit/core/static/css/index.css
imaging_server_kit/core/static/css/info.css
imaging_server_kit/core/templates/index.html
imaging_server_kit/core/templates/info.html
imaging_server_kit/demo/__init__.py
imaging_server_kit/demo/examples.py
imaging_server_kit/demo/sample_images/blobs.tif
imaging_server_kit/demo/sample_images/tracks.tif
imaging_server_kit/template/cookiecutter.json
imaging_server_kit/template/serverkit-{{cookiecutter.name}}/.dockerignore
imaging_server_kit/template/serverkit-{{cookiecutter.name}}/.gitignore
imaging_server_kit/template/serverkit-{{cookiecutter.name}}/Dockerfile
imaging_server_kit/template/serverkit-{{cookiecutter.name}}/README.md
imaging_server_kit/template/serverkit-{{cookiecutter.name}}/docker-compose.yml
imaging_server_kit/template/serverkit-{{cookiecutter.name}}/main.py
imaging_server_kit/template/serverkit-{{cookiecutter.name}}/requirements.txt
imaging_server_kit/template/serverkit-{{cookiecutter.name}}/samples/blobs.tif
imaging_server_kit/types/__init__.py
imaging_server_kit/types/_bool.py
imaging_server_kit/types/_boxes.py
imaging_server_kit/types/_choice.py
imaging_server_kit/types/_float.py
imaging_server_kit/types/_image.py
imaging_server_kit/types/_integer.py
imaging_server_kit/types/_mask.py
imaging_server_kit/types/_notification.py
imaging_server_kit/types/_null.py
imaging_server_kit/types/_paths.py
imaging_server_kit/types/_points.py
imaging_server_kit/types/_string.py
imaging_server_kit/types/_tracks.py
imaging_server_kit-0.1.3.dist-info/licenses/LICENSE
imaging_server_kit-0.1.3.dist-info/METADATA
imaging_server_kit-0.1.3.dist-info/WHEEL
imaging_server_kit-0.1.3.dist-info/entry_points.txt
imaging_server_kit-0.1.3.dist-info/top_level.txt
imaging_server_kit-0.1.3.dist-info/RECORD
