Metadata-Version: 2.4
Name: imaging-server-kit
Version: 0.1.3
Summary: Convert image processing functions to GUIs, FastAPI servers, and more.
Author-email: Mallory Wittwer <mallory.wittwer@epfl.ch>
License: Copyright (c) 2024, EPFL
Project-URL: repository, https://github.com/Imaging-Server-Kit/imaging-server-kit
Project-URL: documentation, https://imaging-server-kit.github.io/imaging-server-kit
Classifier: Development Status :: 2 - Pre-Alpha
Classifier: Intended Audience :: Developers
Classifier: License :: OSI Approved :: BSD License
Classifier: Operating System :: OS Independent
Classifier: Programming Language :: Python
Classifier: Programming Language :: Python :: 3
Classifier: Programming Language :: Python :: 3 :: Only
Classifier: Programming Language :: Python :: 3.9
Classifier: Programming Language :: Python :: 3.10
Classifier: Programming Language :: Python :: 3.11
Classifier: Programming Language :: Python :: 3.12
Classifier: Topic :: Scientific/Engineering :: Image Processing
Requires-Python: >=3.9
License-File: LICENSE
Requires-Dist: numpy
Requires-Dist: tifffile
Requires-Dist: tqdm
Requires-Dist: pydantic>=2.0
Requires-Dist: scikit-image[optional]
Requires-Dist: jinja2
Requires-Dist: PyYAML
Requires-Dist: cookiecutter
Requires-Dist: opencv-contrib-python-headless
Requires-Dist: imantics
Requires-Dist: geojson
Requires-Dist: fastapi
Requires-Dist: uvicorn[standard]
Requires-Dist: python-multipart
Requires-Dist: msgpack
Requires-Dist: httpx
Provides-Extra: docs
Requires-Dist: jupyter-book<2.0; extra == "docs"
Requires-Dist: jupytext; extra == "docs"
Provides-Extra: test
Requires-Dist: pytest; extra == "test"
Provides-Extra: all
Requires-Dist: imaging-server-kit[docs,test]; extra == "all"
Dynamic: license-file
